{
  "project_info": {
    "project_number": "659781802279",
    "firebase_url": "https://femytalk.firebaseio.com",
    "project_id": "femytalk",
    "storage_bucket": "femytalk.appspot.com"
  },
  "client": [
    {
      "client_info": {
        "mobilesdk_app_id": "1:659781802279:android:7da5066f44bd2010",
        "android_client_info": {
          "package_name": "com.femytalk.app"
        }
      },
      "oauth_client": [
        {
          "client_id": "659781802279-39uir8id74lqoi6jbe5302nm2rhse95r.apps.googleusercontent.com",
          "client_type": 3
        }
      ],
      "api_key": [
        {
          "current_key": "AIzaSyAK7nvEYTzWRd2b03Ca7aXXoV2iqYjpn8I"
        }
      ],
      "services": {
        "analytics_service": {
          "status": 1
        },
        "appinvite_service": {
          "status": 1,
          "other_platform_oauth_client": []
        },
        "ads_service": {
          "status": 2
        }
      }
    }
  ],
  "configuration_version": "1"
}